modelindex/__init__.py
modelindex/__main__.py
modelindex/consts.py
modelindex/load_model_index.py
modelindex/utils.py
modelindex/version.py
modelindex/commands/__init__.py
modelindex/commands/cli.py
modelindex/models/BaseModelIndex.py
modelindex/models/Collection.py
modelindex/models/CollectionList.py
modelindex/models/Library.py
modelindex/models/Metadata.py
modelindex/models/Model.py
modelindex/models/ModelIndex.py
modelindex/models/ModelList.py
modelindex/models/Result.py
modelindex/models/ResultList.py
modelindex/models/__init__.py
tests/__init__.py
tests/test_check.py
tests/test_cli.py
tests/test_collections.py
tests/test_examples.py
tests/test_images.py
tests/test_import.py
tests/test_library.py
tests/test_markdown.py
tests/test_singlefile.py
tests/test_str.py
tests/test_yml_head.py
model_index-0.1.11.dist-info/LICENSE
model_index-0.1.11.dist-info/METADATA
model_index-0.1.11.dist-info/WHEEL
model_index-0.1.11.dist-info/entry_points.txt
model_index-0.1.11.dist-info/top_level.txt
model_index-0.1.11.dist-info/RECORD
