Metadata-Version: 2.1
Name: model-index
Version: 0.1.11
Summary: Create a source of truth for ML model results and browse it on Papers with Code
Home-page: https://github.com/paperswithcode/model-index
Author: Robert Stojnic
Author-email: hello@paperswithcode.com
Maintainer: Robert Stojnic
Maintainer-email: hello@paperswithcode.com
License: MIT
Platform: Windows
Platform: POSIX
Platform: MacOSX
